aiohttp_session/__init__.py
aiohttp_session/cookie_storage.py
aiohttp_session/log.py
aiohttp_session/memcached_storage.py
aiohttp_session/nacl_storage.py
aiohttp_session/py.typed
aiohttp_session/redis_storage.py
aiohttp_session-2.12.1.dist-info/LICENSE
aiohttp_session-2.12.1.dist-info/METADATA
aiohttp_session-2.12.1.dist-info/WHEEL
aiohttp_session-2.12.1.dist-info/top_level.txt
aiohttp_session-2.12.1.dist-info/RECORD
