Metadata-Version: 2.1
Name: aiohttp-session
Version: 2.12.1
Summary: sessions for aiohttp.web
Home-page: https://github.com/aio-libs/aiohttp_session/
Author: Andrew Svetlov
Author-email: andrew.svetlov@gmail.com
License: Apache 2
Classifier: License :: OSI Approved :: Apache Software License
Classifier: Intended Audience :: Developers
Classifier: Programming Language :: Python
Classifier: Programming Language :: Python :: 3
Classifier: Programming Language :: Python :: 3.8
Classifier: Programming Language :: Python :: 3.9
Classifier: Programming Language :: Python :: 3.10
Classifier: Programming Language :: Python :: 3.11
Classifier: Programming Language :: Python :: 3.12
Classifier: Programming Language :: Python :: 3.13
Classifier: Topic :: Internet :: WWW/HTTP
Classifier: Framework :: AsyncIO
Classifier: Framework :: aiohttp
License-File: LICENSE
Requires-Dist: aiohttp>=3.10
Provides-Extra: aioredis
Requires-Dist: redis>=4.3.1; extra == "aioredis"
Provides-Extra: aiomcache
Requires-Dist: aiomcache>=0.5.2; extra == "aiomcache"
Provides-Extra: pycrypto
Requires-Dist: cryptography; extra == "pycrypto"
Provides-Extra: secure
Requires-Dist: cryptography; extra == "secure"
Provides-Extra: pynacl
Requires-Dist: pynacl; extra == "pynacl"
